Workbook
Name Slicer_Category: #N/A
Name Slicer_Month: #N/A
Name Slicer_Payment_Method: #N/A

Sheet Raw_Data
A1: Order ID | B1: Customer Name | C1: Food Item | D1: Category | E1: Quantity | F1: Price | G1: Payment Method | H1: Order Time
A2: 2268 | B2: Mary Vega DDS | C2: Pasta | D2: Main | E2: 5 | F2: 16.52 | G2: Cash | H2: 45690.603
A3: 3082 | B3: Brandon Myers | C3: Brownie | D3: Dessert | E3: 4 | F3: 17.27 | G3: Debit Card | H3: 45816.457
A4: 3160 | B4: Margaret Wells | C4: Pasta | D4: Main | E4: 1 | F4: 3.37 | G4: Credit Card | H4: 45720.321
A5: 1272 | B5: Michael Matthews | C5: Pasta | D5: Main | E5: 5 | F5: 2.2 | G5: Online Payment | H5: 45792.53
A6: 9447 | B6: Connor Williams | C6: Soup | D6: Starter | E6: 1 | F6: 12.23 | G6: Cash | H6: 45731.601
A7: 1587 | B7: Matthew Miles | C7: Brownie | D7: Dessert | E7: 5 | F7: 7.39 | G7: Credit Card | H7: 45759.243
A8: 2834 | B8: Catherine Thompson | C8: Soup | D8: Starter | E8: 3 | F8: 8.31 | G8: Credit Card | H8: 45828.764
A9: 4514 | B9: Nathan Holland | C9: Soup | D9: Starter | E9: 4 | F9: 2.28 | G9: Cash | H9: 45807.392
A10: 3946 | B10: Anthony Sherman | C10: Pasta | D10: Main | E10: 1 | F10: 13.05 | G10: Credit Card | H10: 45811.071
A11: 3174 | B11: Carolyn Roberts | C11: Cake | D11: Dessert | E11: 4 | F11: 19.48 | G11: Cash | H11: 45856.041
A12: 8018 | B12: Johnny Dennis | C12: Burger | D12: Main | E12: 5 | F12: 11.79 | G12: Debit Card | H12: 45775.34
A13: 5134 | B13: Michael Barton | C13: Cake | D13: Dessert | E13: 1 | F13: 20.73 | G13: Online Payment | H13: 45693.024
... A501: 1509 | B501: Amber Mendez | C501: Ice Cream | D501: Dessert | E501: 2 | F501: 18.86 | G501: Online Payment | H501: 45878.216

Sheet restaurant_orders
A1: Order ID | B1: Customer Name | C1: Food Item | D1: Category | E1: Quantity | F1: Price | G1: Price Category | H1: Cost | I1: Total Sales | J1: Profit | K1: Profit_Margin | L1: Payment Method | M1: Order Date | N1: Order Time | O1: Month | P1: Day | Q1: Day Type | R1: Hour | S1: Time Period
A2: 1329 | B2: Monique Gonzalez | C2: Burger | D2: Main | E2: 1 | F2: 20.63 | G2: =IF(F2<10,"Budget",IF(F2<20,"Mid-Range","Premium")) -> Premium | H2: =60% * F2 -> 12.378 | I2: =E2 * F2 -> 20.63 | J2: =I2 - H2 -> 8.252 | K2: =J2 / I2 -> 0.4 | L2: Cash | M2: 45658.067 | N2: 45658.067 | O2: =TEXT(N2,"MMM") -> Jan | P2: =TEXT(M2, "DDD") -> Wed | Q2: =IF(OR(P2="Fri",P2="Sat"),"Weekend","Weekday") -> Weekday | R2: =HOUR(N2) -> 1 | S2: Morning
A3: 2065 | B3: Jade Gilbert | C3: Burger | D3: Main | E3: 4 | F3: 19.86 | G3: =IF(F3<10,"Budget",IF(F3<20,"Mid-Range","Premium")) -> Mid-Range | H3: =60% * F3 -> 11.916 | I3: =E3 * F3 -> 79.44 | J3: =I3 - H3 -> 67.524 | K3: =J3 / I3 -> 0.85 | L3: Online Payment | M3: 45659.442 | N3: 45659.442 | O3: =TEXT(N3,"MMM") -> Jan | P3: =TEXT(M3, "DDD") -> Thu | Q3: =IF(OR(P3="Fri",P3="Sat"),"Weekend","Weekday") -> Weekday | R3: =HOUR(N3) -> 10 | S3: Morning
A4: 1489 | B4: James Moran | C4: Ice Cream | D4: Dessert | E4: 4 | F4: 10 | G4: =IF(F4<10,"Budget",IF(F4<20,"Mid-Range","Premium")) -> Mid-Range | H4: =60% * F4 -> 6 | I4: =E4 * F4 -> 40 | J4: =I4 - H4 -> 34 | K4: =J4 / I4 -> 0.85 | L4: Cash | M4: 45659.658 | N4: 45659.658 | O4: =TEXT(N4,"MMM") -> Jan | P4: =TEXT(M4, "DDD") -> Thu | Q4: =IF(OR(P4="Fri",P4="Sat"),"Weekend","Weekday") -> Weekday | R4: =HOUR(N4) -> 15 | S4: Afternoon
A5: 4212 | B5: Juan Lucero | C5: Fries | D5: Starter | E5: 5 | F5: 15.29 | G5: =IF(F5<10,"Budget",IF(F5<20,"Mid-Range","Premium")) -> Mid-Range | H5: =60% * F5 -> 9.174 | I5: =E5 * F5 -> 76.45 | J5: =I5 - H5 -> 67.276 | K5: =J5 / I5 -> 0.88 | L5: Debit Card | M5: 45659.66 | N5: 45659.66 | O5: =TEXT(N5,"MMM") -> Jan | P5: =TEXT(M5, "DDD") -> Thu | Q5: =IF(OR(P5="Fri",P5="Sat"),"Weekend","Weekday") -> Weekday | R5: =HOUR(N5) -> 15 | S5: Afternoon
A6: 4811 | B6: Steven Larson | C6: Salad | D6: Starter | E6: 5 | F6: 8.06 | G6: =IF(F6<10,"Budget",IF(F6<20,"Mid-Range","Premium")) -> Budget | H6: =60% * F6 -> 4.836 | I6: =E6 * F6 -> 40.3 | J6: =I6 - H6 -> 35.464 | K6: =J6 / I6 -> 0.88 | L6: Cash | M6: 45660.255 | N6: 45660.255 | O6: =TEXT(N6,"MMM") -> Jan | P6: =TEXT(M6, "DDD") -> Fri | Q6: =IF(OR(P6="Fri",P6="Sat"),"Weekend","Weekday") -> Weekend | R6: =HOUR(N6) -> 6 | S6: Morning
A7: 2391 | B7: Denise Thompson | C7: Salad | D7: Starter | E7: 1 | F7: 9.02 | G7: =IF(F7<10,"Budget",IF(F7<20,"Mid-Range","Premium")) -> Budget | H7: =60% * F7 -> 5.412 | I7: =E7 * F7 -> 9.02 | J7: =I7 - H7 -> 3.608 | K7: =J7 / I7 -> 0.4 | L7: Debit Card | M7: 45661.048 | N7: 45661.048 | O7: =TEXT(N7,"MMM") -> Jan | P7: =TEXT(M7, "DDD") -> Sat | Q7: =IF(OR(P7="Fri",P7="Sat"),"Weekend","Weekday") -> Weekend | R7: =HOUR(N7) -> 1 | S7: Morning
A8: 7960 | B8: Diana House | C8: Cake | D8: Dessert | E8: 3 | F8: 5.09 | G8: =IF(F8<10,"Budget",IF(F8<20,"Mid-Range","Premium")) -> Budget | H8: =60% * F8 -> 3.054 | I8: =E8 * F8 -> 15.27 | J8: =I8 - H8 -> 12.216 | K8: =J8 / I8 -> 0.8 | L8: Cash | M8: 45661.283 | N8: 45661.283 | O8: =TEXT(N8,"MMM") -> Jan | P8: =TEXT(M8, "DDD") -> Sat | Q8: =IF(OR(P8="Fri",P8="Sat"),"Weekend","Weekday") -> Weekend | R8: =HOUR(N8) -> 6 | S8: Morning
A9: 9126 | B9: Dale Salinas | C9: Brownie | D9: Dessert | E9: 5 | F9: 23.28 | G9: =IF(F9<10,"Budget",IF(F9<20,"Mid-Range","Premium")) -> Premium | H9: =60% * F9 -> 13.968 | I9: =E9 * F9 -> 116.4 | J9: =I9 - H9 -> 102.432 | K9: =J9 / I9 -> 0.88 | L9: Credit Card | M9: 45662.272 | N9: 45662.272 | O9: =TEXT(N9,"MMM") -> Jan | P9: =TEXT(M9, "DDD") -> Sun | Q9: =IF(OR(P9="Fri",P9="Sat"),"Weekend","Weekday") -> Weekday | R9: =HOUR(N9) -> 6 | S9: Morning
A10: 5359 | B10: Teresa Rollins | C10: Ice Cream | D10: Dessert | E10: 5 | F10: 19.48 | G10: =IF(F10<10,"Budget",IF(F10<20,"Mid-Range","Premium")) -> Mid-Range | H10: =60% * F10 -> 11.688 | I10: =E10 * F10 -> 97.4 | J10: =I10 - H10 -> 85.712 | K10: =J10 / I10 -> 0.88 | L10: Cash | M10: 45662.335 | N10: 45662.335 | O10: =TEXT(N10,"MMM") -> Jan | P10: =TEXT(M10, "DDD") -> Sun | Q10: =IF(OR(P10="Fri",P10="Sat"),"Weekend","Weekday") -> Weekday | R10: =HOUR(N10) -> 8 | S10: Morning
A11: 4855 | B11: Todd Brown | C11: Cake | D11: Dessert | E11: 2 | F11: 4.09 | G11: =IF(F11<10,"Budget",IF(F11<20,"Mid-Range","Premium")) -> Budget | H11: =60% * F11 -> 2.454 | I11: =E11 * F11 -> 8.18 | J11: =I11 - H11 -> 5.726 | K11: =J11 / I11 -> 0.7 | L11: Credit Card | M11: 45662.86 | N11: 45662.86 | O11: =TEXT(N11,"MMM") -> Jan | P11: =TEXT(M11, "DDD") -> Sun | Q11: =IF(OR(P11="Fri",P11="Sat"),"Weekend","Weekday") -> Weekday | R11: =HOUR(N11) -> 20 | S11: Evening
A12: 8184 | B12: Amanda Keller | C12: Brownie | D12: Dessert | E12: 2 | F12: 8.43 | G12: =IF(F12<10,"Budget",IF(F12<20,"Mid-Range","Premium")) -> Budget | H12: =60% * F12 -> 5.058 | I12: =E12 * F12 -> 16.86 | J12: =I12 - H12 -> 11.802 | K12: =J12 / I12 -> 0.7 | L12: Debit Card | M12: 45664.234 | N12: 45664.234 | O12: =TEXT(N12,"MMM") -> Jan | P12: =TEXT(M12, "DDD") -> Tue | Q12: =IF(OR(P12="Fri",P12="Sat"),"Weekend","Weekday") -> Weekday | R12: =HOUR(N12) -> 5 | S12: Morning
A13: 8629 | B13: Mrs. Melissa Schmidt | C13: Burger | D13: Main | E13: 1 | F13: 9.28 | G13: =IF(F13<10,"Budget",IF(F13<20,"Mid-Range","Premium")) -> Budget | H13: =60% * F13 -> 5.568 | I13: =E13 * F13 -> 9.28 | J13: =I13 - H13 -> 3.712 | K13: =J13 / I13 -> 0.4 | L13: Debit Card | M13: 45664.318 | N13: 45664.318 | O13: =TEXT(N13,"MMM") -> Jan | P13: =TEXT(M13, "DDD") -> Tue | Q13: =IF(OR(P13="Fri",P13="Sat"),"Weekend","Weekday") -> Weekday | R13: =HOUR(N13) -> 7 | S13: Morning
... A501: 9086 | B501: James Nixon | C501: Soup | D501: Starter | E501: 1 | F501: 10.32 | G501: =IF(F501<10,"Budget",IF(F501<20,"Mid-Range","Premium")) -> Mid-Range | H501: =60% * F501 -> 6.192 | I501: =E501 * F501 -> 10.32 | J501: =I501 - H501 -> 4.128 | K501: =J501 / I501 -> 0.4 | L501: Online Payment | M501: 45883.306 | N501: 45883.306 | O501: =TEXT(N501,"MMM") -> Aug | P501: =TEXT(M501, "DDD") -> Thu | Q501: =IF(OR(P501="Fri",P501="Sat"),"Weekend","Weekday") -> Weekday | R501: =HOUR(N501) -> 7 | S501: Morning

Sheet Pivot_Table
H1: Items | I1: Sum of Total Sales
A2: Month | B2: Sum of Total Sales | H2: Cake | I2: 2236.58 | K2: Time period | L2: Sum of Total Sales | N2: Payment method | O2: Sum of Total Sales
A3: Jan | B3: 2015.48 | D3: Category | E3: Sum of Total Sales | H3: Pasta | I3: 2267.73 | K3: Afternoon | L3: 6027.89 | N3: Cash | O3: 5197.68
A4: Feb | B4: 2598.72 | D4: Dessert | E4: 6509.99 | H4: Fries | I4: 2340.48 | K4: Evening | L4: 4568.34 | N4: Credit Card | O4: 5322.98
A5: Mar | B5: 3237.43 | D5: Main | E5: 7026.79 | H5: Brownie | I5: 2570.19 | K5: Morning | L5: 9426.91 | N5: Debit Card | O5: 4620.73
A6: Apr | B6: 2576.14 | D6: Starter | E6: 6486.36 | H6: Pizza | I6: 2627.89 | K6: Grand Total | L6: 20023.14 | N6: Online Payment | O6: 4881.75
A7: May | B7: 2622.53 | D7: Grand Total | E7: 20023.14 | H7: Grand Total | I7: 12042.87 | N7: Grand Total | O7: 20023.14
A8: Jun | B8: 2602.6
A9: Jul | B9: 3313.64
A10: Aug | B10: 1056.6
A11: Grand Total | B11: 20023.14
A16: Item | B16: Sum of Quantity | D16: Day | E16: Sum of Profit | G16: Day | H16: Sum of Total Sales | J16: Moth | K16: Sum of Profit | M16: Category | N16: Sum of Quantity | P16: Day type | Q16: Sum of Total Sales
A17: Pizza | B17: 200 | D17: Sun | E17: 2688.478 | G17: Sun | H17: 3347.86 | J17: Jan | K17: 1606.556 | M17: Dessert | N17: 504 | P17: Weekday | Q17: 14655.31
A18: Brownie | B18: 192 | D18: Mon | E18: 2347.874 | G18: Mon | H18: 2879.42 | J18: Feb | K18: 2114.58 | M18: Main | N18: 523 | P18: Weekend | Q18: 5367.83
A19: Fries | B19: 179 | D19: Tue | E19: 1889.548 | G19: Tue | H19: 2443.99 | J19: Mar | K19: 2592.844 | M19: Starter | N19: 488 | P19: Grand Total | Q19: 20023.14
A20: Burger | B20: 169 | D20: Wed | E20: 2238.274 | G20: Wed | H20: 2887.33 | J20: Apr | K20: 2041.162 | M20: Grand Total | N20: 1515
A21: Cake | B21: 164 | D21: Thu | E21: 2548.31 | G21: Thu | H21: 3096.71 | J21: May | K21: 2128.712
A22: Salad | B22: 159 | D22: Fri | E22: 2376.204 | G22: Fri | H22: 2872.44 | J22: Jun | K22: 2083.69
A23: Pasta | B23: 154 | D23: Sat | E23: 1975.298 | G23: Sat | H23: 2495.39 | J23: Jul | K23: 2672.696
A24: Soup | B24: 150 | D24: Grand Total | E24: 16063.986 | G24: Grand Total | H24: 20023.14 | J24: Aug | K24: 823.746
A25: Ice Cream | B25: 148 | J25: Grand Total | K25: 16063.986
A26: Grand Total | B26: 1515

Sheet KPI
A1: Total sales | B1: =COUNTA(restaurant_orders!E:E)-1 -> 500
A2: Total Item Sold | B2: =SUM(restaurant_orders!E:E) -> 1515
A3: Avg Items per order | B3: =SUM(restaurant_orders!E:E)/(COUNTA(restaurant_orders!A:A)-1) -> 3.03
A4: Total revenue | B4: =SUM(restaurant_orders!I:I) -> 20023.14
A5: Total profit | B5: =SUM(restaurant_orders!J:J) -> 16063.986
A6: Profit Margin | B6: =SUM(restaurant_orders!J:J)/SUM(restaurant_orders!I:I) -> 0.80227107
A23: Total sales | B23: =COUNTA(restaurant_orders!E:E)-1 -> 500
A24: Total Item Sold | B24: =SUM(restaurant_orders!E:E) -> 1515
A25: Avg Items per order | B25: =SUM(restaurant_orders!E:E)/(COUNTA(restaurant_orders!A:A)-1) -> 3.03
A26: Total revenue | B26: =SUM(restaurant_orders!I:I) -> 20023.14
A27: Total profit | B27: =SUM(restaurant_orders!J:J) -> 16063.986
A28: Profit Margin | B28: =SUM(restaurant_orders!J:J)/SUM(restaurant_orders!I:I) -> 0.80227107

Sheet Dashboard
